{  "metadata": {
        "title": "Pysy modality Elicitation 2023",
        "speakers": "Pysy",
        "linguists": "Myriam Lapierre, Ella De Falco, Sunkulp Ananthanarayan",
        "date": "June/July? 2023",
        "type": "elicitation"
    },	
    "sentences" : [{"transcription": "Saankôrä hä kypy sarërï tapja hokjya",
"translation": "Deve ser Sankoora está lendo mensagens"},
{"transcription": "Huwahä kypy pam Tepakriti pârankôjönkwa rï ",
"translation": "Deve ser Tepakriti deve estár na farmacia."},
{"transcription": "Mära hä kypy rö ponpo kjäkôn kja hamä",
"translation": "deve ser gilete está naquela última sacola"},
{"transcription": "mära hä kypy rö ponpo pakkjapên kja hamä",
"translation": "deve ser está naquela primeira"},
{"transcription": "mära hä kypy rö ponpo ippôri kja hamä",
"translation": "deve ser o gilete está naquele do meio"},
{"transcription": "kypyppa pjo Krerö kukre hamä",
"translation": "deve ser Krerö não está en casa."},
{"transcription": "kypyppa pjo Krerö kukre rï ",
"translation": "deve ser Krerö não está en casa."},
{"transcription": "Kypyppa pjo tapja Krerö kukre hamä",
"translation": "não sei se Krerö está em casa"},
{"transcription": "innë, Jopy kypy kwyjn tapja tessuu inkô tä",
"translation": "eu não sei, deve ser Jopy foi pescar no rio"},
{"transcription": "Jopy kypy kwyjn tapja tessuu inkô tä",
"translation": "deve ser o Jopy foi pescar no rio"},
{"transcription": "ja hahä kypy kjyjn tapja Brasília rï ",
"translation": "deve ser está frio em Brasília"},
{"transcription": "koomä kypy kjyjn tapja Brasília rï",
"translation": "deve ser está frio em Brasília agora/hoje"},
{"transcription": "märahä intokâttâjn Tepakriti, mämäramä sössy pô(jn)",
"translation": "deve ser o Tepakriti está, acordado, por isso ele está ligando a luz"},
{"transcription": "märahä",
"translation": "deve ser estar aí"},
{"transcription": "Tepakriti kypyntokâtlâjn, mämäramä sössy pô",
"translation": "Tepakriti deve estar acordado aindo (não dorme ainda), por isso a luz dele está ligada."},
{"transcription": "suppôô kin pjo Bep'ere pârankô suu",
"translation": "Bep'ere não deve ser estar tomando direito o remédio"},
{"transcription": "Suppôja hê pjo tapja Bep’ere koomä pârankô suu",
"translation": "deve ser hoje Bep’ere não vai vir tomar remédio"},
{"transcription": "Kati py su pôô tapja Bep’ere koomä, pârankô suu",
"translation": "deve ser hoje Bep’ere vai vir tomar remédio"},
{"transcription": "innë, kati py su pôô tapja Bep’ere koomä, pârankô suu",
"translation": "deve ser hoje Bep’ere vai vir tomar remédio"},
{"transcription": "mära hä topintori sönkresê kjêpyti hë",
"translation": "pode ser Kjepyti perdeu o colar"},
{"transcription": "Mära hä tisïrï jukôpy",
"translation": "deve ser ela deixou nalgum lugar"},
{"transcription": "Mära hä kypy hatojn jattä",
"translation": "pode ser que ele saiu da frente da casa"},
{"transcription": "mära hä kypymmöri mäjatittä",
"translation": "pode ser que ele saiu da frente da casa"},
{"transcription": "mära hä kypyppa kukre kjäti ",
"translation": "pode ser ele está atrás da casa"},
{"transcription": "mära hä kypy hatojn jattä, mära hä kypy hatojn mäjattä",
"translation": "deve ser ele saiu para cá, ou ele saiu para lá"},
{"transcription": "mära hä kypy hatojn kukre toti tä, mära hä kypy hatojn kukre swa tä",
"translation": "deve ser saiu atrás da casa, ou saiu para a frente da casa"},
{"transcription": "Kypy too tapja Sâsürä Sökârasä tä.",
"translation": "deve ser Sâsürä foi para Sökâräsä"},
{"transcription": "Sâsürä jy tën jïïpê Sökârasätä",
"translation": "Sâsürä foi direto (sem parar) para Sökârasä"},
{"transcription": "(innë), kypy too tapja sâsürä sökârasä tä",
"translation": "não sei, deve ser Sâsürä foi para Sökârasä"},
{"transcription": "Kypyppa pjo tapja Kôpyn ",
"translation": "deve ser Kôpyn não está aí"},
{"transcription": "Kypyppa pjo tapja Kôpyn, juri sä(rïn) sö moto?",
"translation": "deve ser K não está, cadê a moto dele?"},
{"transcription": "märahä jyttoo",
"translation": "deve ser ele já foi embora"},
{"transcription": "Tutiti ippa hahê pjo kukre rï",
"translation": "Tutiti deve ser não está en casa."},
{"transcription": "Tutiti ippa hahê pjo kukre rï, jïïpê kati pan puu tä",
"translation": "T não deve estar en casa, sempre ela tem que ir para a roça"},
{"transcription": "Tutiti ippa hahê pjo kukre rï, jïïpê kati pan inpyti köö puu tä",
"translation": "Tutiti deve ser não está em casa, sempre ela vai pra roça nessa hora"},
{"transcription": "Kati sankjân hä moto kjäkâ",
"translation": "tem que usar capacete"},
{"transcription": "visitantes kati py pôjn 6 hora rï ",
"translation": "visitante pode sair 6 horas"},
{"transcription": "visitantes kati py hatojn 6 hora rï",
"translation": "visitante tem que sair ás 6 horas"},
{"transcription": "Inkjë hë tärãĩjĩtopê toja hê",
"translation": "eu deveria pintar meu rosto para dançar"},
{"transcription": "Ka rê tä têpi rö ipjo, nänkjo hä ",
"translation": "não pode chegar perto"},
{"transcription": "mära tapja nänkjo, covid",
"translation": "essa doença deve ser covid"},
{"transcription": "Kati sên sikja sörïn sâpêrä hê",
"translation": "lava as mãos para você trabalhar"},
{"transcription": "Kamërân kati rêsên sikja sörïn sö hahê",
"translation": "Deveria vcs lavar as mãos pra fazer comida"},
{"transcription": "Kamërân kati rêsê sankjârïn sakrehapu sâpêrä hê",
"translation": "Y all should use a mask in order to work"},
{"transcription": "Tetâta hë kati wajäriïn ippeënkân",
"translation": "Tetââta can do the recording"},
{"transcription": "Tetâta hë tiwajäriï pjärä ippeënkjân, inkjon tapja",
"translation": "Tetââta could do the recording but(/or) doesn't have to"},
{"transcription": "Pÿrä hä kati rê su hankjân",
"translation": "One at a time you can go in"},
{"transcription": "ha kati tökrëë kjäpo?",
"translation": "are you going to eat beijú?"},
{"transcription": "ha kati më tökrëë kjäpo?",
"translation": "are y'all going to eat beijú?"},
{"transcription": "Hê, ka kukrëë pjärä kjäpo, ou kati sê haswâra mä",
"translation": "You can eat beiju or you can bathe."},
{"transcription": "Ka kukrëë pjärä kjäpo, ou kati swâra mä",
"translation": "You can eat beiju or you can bathe."},
{"transcription": "Kati kukrëë kjäpo ou kati sê haswâri hä",
"translation": "se você vai comer beiju ou você pode banhar"},
{"transcription": "tuukô heë kati py sanpâ wêntwê, suppôô pjo ti py sanpârä hê wêntwê",
"translation": "Tuuko has permission to pick the baby up, but can't manage to pick up the baby"},
{"transcription": "Ka tä sanpânnö hahê pjo wêntwê",
"translation": "You do not have permission to carry the baby"},
{"transcription": "Ja pên kati py sanpârin wêntwê",
"translation": "You now have permission to carry the baby"},
{"transcription": "huwähä kati sa pâsâjn",
"translation": "You can enter there"},
{"transcription": "Pysy kati sapykwyjn, susââ pjo, ti tãpjori sakwa.",
"translation": "Pysy has permission to enter, he isn't able to, the door is closed"},
{"transcription": "Ka hẽ kati põrĩn tepi",
"translation": "você pode assar peixe"},
{"transcription": "Ka hẽ kati pô tepi",
"translation": "você pode assar peixe"},
{"transcription": "ka hẽ katinkjẽ sakrejn, juttä ro hon rẽ pôra hê tepi",
"translation": "você pode me ensinar como assar peixe"},
{"transcription": "ta rappôri tapja inkjẽ hẽ tepi, rênpari pjo tepi rêppôra hê",
"translation": "eu poderia assar peixe, mas eu não sei assar peixe."},
{"transcription": "inkjẽ hẽ tãra jĩntoopê, rêntoopê hahê pjo",
"translation": "Eu deveria pintar meu rosto, mas não vou pintar"},
{"transcription": "tãra jokjy, nãhã rê jokjy hahê pjo",
"translation": "Eu deveria pintar, mas não preciso pintar"},
{"transcription": "kamẽrân karêsankjân sakre hapuha, inkjon tapja",
"translation": "Vocês poderiam usar máscara, mas não precisa usar"},
{"transcription": "Moto kjãkâ kati sankjârin ho hãanpjaja hê moto ho",
"translation": "você poderia usar capacete para você dirigir moto"},
{"transcription": "ka hẽ kati sê sankjârĩn moto kjãkâ, moto hahê",
"translation": "você tem que usar capacete para você dirigir moto."},
{"transcription": "ka hẽ kati sê sankjârĩn moto kjãkâ, moto hanpjaja hê",
"translation": "você tem que usar capacete para você dirigir moto."},
{"transcription": "hanpja rõ hahê pjo kjãkâkjên, moto hamã",
"translation": "você não pode dirigir moto sem capacete"},
{"transcription": "ka sânpũnnõ hahê pjo ka krippjâ",
"translation": "você não pode olhar seu sogro"},
{"transcription": "mã happẽẽ rõ hahê pjo ka krippjânkjên mã",
"translation": "você não pode falar para sua sogra"},
{"transcription": "krerõhantêrân rêkura hê pjo sãkkjâri",
"translation": "K não pode comer comida (da resta)"},
{"transcription": "swasâja hê pjo, jyy pjon inpyti",
"translation": "vocês não pode entrar, já acabou o horario de visita."},
{"transcription": "(su)ha sâja hê pjo. 6 hora rĩ",
"translation": "vocês não pode entrar depois das 6 horas."},
{"transcription": "ka kati hatërïn kypa kjäkâtâtä",
"translation": "você tem que ir na BR"},
{"transcription": "Nänsêpotiti hë kati pê hopô hän sokjentita sönkâräsä pê",
"translation": "NSPT tem que fazer gol pra SKRS perder"},
{"transcription": "Nänsêpotiti hë kati sê hopôjn sokjentita, tinpârä hê ippëpää",
"translation": "NSPT tem que fazer gol para pegar trofeo"},
{"transcription": "kahë kati mäsürïn tupyn mä ti pja käntö wajära hê sikkreekô ka mä",
"translation": " você tem que falar para Tupyn para ela fazer outros brincos para você"},
{"transcription": "rêhammöra hë Nänpôôröö tä, kôkjati pita mä kati rê hammörïn Nänpôôröö tä",
"translation": "para vocês ir para N, vocês tem que ir no carro para N."},
{"transcription": "märämä kati rê hammörïn Valdemiro hamä",
"translation": "deveria vocês ir no carro do Valdemiro"},
{"transcription": "Inkjë ka py sapyntitin kjasê jopê",
"translation": "eu deveria procurar cinto"},
{"transcription": "Inkjë ka py sapyntitin kjasê japê, mämä rasuppôô kïrïn inkjë suu",
"translation": "eu vou procurar aquele cinto que serve bem (that fits me well)"},
{"transcription": "Kjë hë ka mïrïn kreejää kjê hamä",
"translation": "I will bake taro on the earth oven"},
{"transcription": "Kjë hë ka kusari kreejââ inkô hamä",
"translation": "I will boil taro in the water"},
{"transcription": "Kjë hë kapôrin kreejââ issy hamä",
"translation": "I will grill taro on the fire"},
{"transcription": "Inkjë hë ka kusarin kreejââ inkô jamä",
"translation": "eu posso cozinhar cará na água"},
{"transcription": "Japjârân kati mï wajärïn ippëë sala 6 hamä",
"translation": "a gente pode fazer reunião na sala 6."},
{"transcription": "Japjârân kati mï wajärïn ippëë, pjärämä? Sala 5 hamä ou sala 6 hamä?",
"translation": "nós vamos fazer reunião na sala 5 ou na sala 6?"},
{"transcription": "Tö pyri kôtita Del Mouro hamä",
"translation": "pode comprar frango no del M."},
{"transcription": "Tö pyri kôtita Casa Aurora hamä",
"translation": "pode comprar frango no Casa A."},
{"transcription": "Rê sê kunkwâri kôtita Del Mouro hamä",
"translation": "vocês pode comprar frango de Del Moro"},
{"transcription": "Sê më tö pyri kôtita Del Mouro hamä",
"translation": "Vocês (2) pode comprar frango no DM"},
{"transcription": "Rë hammörï pjärä kôkjatipitomä, rê py hammöra hê pjo kôkjati pitamä Nänpööröö tä",
"translation": "vocês poderiam ir de carro, mas não precisa ir de carro para N."},
{"transcription": "Hatënnö pjärä kôkjati pita mä Nänpööröö tä",
"translation": "não precisa ir de carro para N"},
{"transcription": "Inkjon pjy tö",
"translation": "não tem outra estrada"},
{"transcription": "Kati hatërin Sinopi tä pjy kjä kâtâti hä, inkjon pjy tö. Mämä pyti.",
"translation": "Você pode ir para Sinopi no BR. Não tem outro, aquele é único."},
{"transcription": "Hatënnö hahê pjo pjy tö hä",
"translation": "Não pode ir no outro estada"},
{"transcription": "Nänsêpotiti mëra rê hatoo rö hahê pjo",
"translation": "NSPT não pode perder"},
{"transcription": "Ra sââ jatoonpe",
"translation": "Eu tô com muito vontade de mijar"},
{"transcription": "Inkjë ka sakriti(n)",
"translation": "Eu preciso espirrar"},
{"transcription": "Inkjë ka sakriti wyn",
"translation": "Eu vou espirrar muito"},
{"transcription": "Inkô katinpja jattä",
"translation": "Agua vai passa por aqui"},
{"transcription": "Inkô kati pê pjorin",
"translation": "Fecha (registro da) água"},
{"transcription": "Mäja kôpy kati pê pjorin, mämän pên inkô katinpja mäjattä",
"translation": "Fecha (registro) aquí, e a água vai passar para cá"},
{"transcription": "Pakwa tejy më, kypamä tuha pjâ pjo Xingu rï",
"translation": "Pakwa tejy & kypamä didn't grow in the Xingu"},
{"transcription": "Kypamätuha kati pjân Tapajuna jö kypa hamä",
"translation": "Banana pode crescer muito na terra do Tapajuna"},
{"transcription": "Kypamätuha pjâ hahê pjo kâsapi jö kypa hamä",
"translation": "O banana não pode crescer na terra do Kayabi"},
{"transcription": "Kjêpyti hë wajärï pjärïn kjäpo kânpo, mä sê soti pjo",
"translation": "Kjêpyti quer fazer bolo mas não tem mistura pra fazer bolo"},
{"transcription": "Kyêpyti hë kati wajä kjäpo kânpo",
"translation": "Kjêpyti pode fazer bolo"},
{"transcription": "Kjêpyti hë kati wajä kjäpo kânpo, mä sê soti pjo",
"translation": "Kjêpyti pode fazer bolo, mas não tem nada para fazer"},
{"transcription": "Kôpyn kati py pan",
"translation": "Kôpyn pode andar"},
{"transcription": "Kôpyn jy py pa",
"translation": "Kôpyn consegue andar"},
{"transcription": "Kôpyn jy py pa, inkjon, timä süri pjo tôtô hë",
"translation": "Kôpyn consegue andar, mas doutor falou para ele não andar"},
{"transcription": "Kjë krippjâ sâpêrä tän, söpää japjârân rê mä sün pjo sâpêrä hê",
"translation": "minha sogra ainda faz comida, os filhos não deixam ela trabalhar"},
{"transcription": "Kjë krippjâ ti sotinkwâratän, söpää japjârân rê mä sün pjo sâpê rä hê",
"translation": "minha sogra ainda faz comida, os filhos dela não deixam ela trabalhar"},
{"transcription": "Kjë krippjâ ti sotinkwâra tän",
"translation": "minha sogra ainda faz comida"},
{"transcription": "Kjë krippjâ hë ti wajära tän sö",
"translation": "minha sogra ainda faz comida"},
{"transcription": "Valdemiro jö kôkjati pita mä rankjân 5 mëra",
"translation": "no carro do Valdemiro cabe 5 pessoas"},
{"transcription": "Valdemiro jö kôkjati pita mä rankjân 5 mëra, rankjân 4 mëra",
"translation": "no carro do Valdemiro cabe 5 pessoas, não pode ser 5, tem que ser 4"},
{"transcription": "inta katinkwân tapja nöpjö sokjentita hä",
"translation": "deve ser chuva vai chover ou 5 ou 6 meses."},
{"transcription": "inta katinkwân 6 meses hahä",
"translation": "deve ser chuva vai chover até 6 meses."},
{"transcription": "innë, katinkwân tapja inta 5 meses hahä",
"translation": "não sei, deve chuva vai chover até 5 meses."},
{"transcription": "innë, katinkwâ rö hahê tapja inta 6 meses",
"translation": "não sei, deve ser a chuva não vai chover 6 meses."},
{"transcription": "Katinkwâ rö hahê tapja inta 6 meses",
"translation": "deve ser a chuva não vai chover 6 meses."},
{"transcription": "inkwâ rö hahê pjo inta hakärä hä",
"translation": "deve ser a chuva não pode chover na época da seca."},
{"transcription": "Kôpyn ippa pjo",
"translation": "Kôpyn não consegue andar"},
{"transcription": "inkô inpja rö hahê pjo mäjattä",
"translation": "água não pode passar para cá"},
{"transcription": "mäja rajï pyri pjärïn, paakâ kjäpô, (kjë kin) ",
"translation": "esse tênis eu quero comprar (por que eu gostei muito)."},
{"transcription": "kjë hë kaj̃ï pyrin, (kjë kïrä mä)",
"translation": "eu vou comprar (porque eu gostei muito)"},
{"transcription": "kjë hë ka sapjôrin mära inkjên",
"translation": "eu vou casar esta mulher."},
{"transcription": "inkjë ra tën pjärïn rê tä raanpärä hë sokjentita hä nänsêpotiti tä",
"translation": "Eu quero ir pra mim ver o jogo na aldeia NSPT"},
{"transcription": "inkjë ka tërïn rêsânpürä hê sokjentita",
"translation": "eu vou para mim ver o jogo"},
{"transcription": "kjë näpjâ mÿnkjâjn ti raanpärä hê inkjë",
"translation": "minha tia quer vir para acá para me visitar."}]}